<?xml version="1.0" encoding="UTF-8" standalone="yes"?>
<p:sldLayout xmlns:a="http://schemas.openxmlformats.org/drawingml/2006/main" xmlns:r="http://schemas.openxmlformats.org/officeDocument/2006/relationships" xmlns:p="http://schemas.openxmlformats.org/presentationml/2006/main" showMasterSp="0" type="picTx" preserve="1"><p:cSld name="Picture with Caption"><p:spTree><p:nvGrpSpPr><p:cNvPr id="1" name=""/><p:cNvGrpSpPr/><p:nvPr/></p:nvGrpSpPr><p:grpSpPr><a:xfrm><a:off x="0" y="0"/><a:ext cx="0" cy="0"/><a:chOff x="0" y="0"/><a:chExt cx="0" cy="0"/></a:xfrm></p:grpSpPr><p:sp><p:nvSpPr><p:cNvPr id="2" name="Title 1"/><p:cNvSpPr><a:spLocks noGrp="1"/></p:cNvSpPr><p:nvPr><p:ph type="title"/></p:nvPr></p:nvSpPr><p:spPr><a:xfrm><a:off x="457200" y="500856"/><a:ext cx="8229600" cy="674688"/></a:xfrm><a:ln><a:solidFill><a:schemeClr val="accent1"/></a:solidFill></a:ln></p:spPr><p:txBody><a:bodyPr lIns="274320" anchor="ctr"/><a:lstStyle><a:lvl1pPr algn="r"><a:buNone/><a:defRPr sz="2000" b="0"><a:solidFill><a:schemeClr val="tx1"/></a:solidFill></a:defRPr></a:lvl1pPr></a:lstStyle><a:p><a:r><a:rPr lang="en-US" smtClean="0"/><a:t>Click to edit Master title style</a:t></a:r><a:endParaRPr lang="en-US" dirty="0"/></a:p></p:txBody></p:sp><p:sp><p:nvSpPr><p:cNvPr id="3" name="Picture Placeholder 2"/><p:cNvSpPr><a:spLocks noGrp="1"/></p:cNvSpPr><p:nvPr><p:ph type="pic" idx="1"/></p:nvPr></p:nvSpPr><p:spPr><a:xfrm><a:off x="457200" y="1905000"/><a:ext cx="8229600" cy="4270248"/></a:xfrm><a:solidFill><a:schemeClr val="tx1"><a:shade val="50000"/></a:schemeClr></a:solidFill><a:ln><a:noFill/></a:ln><a:effectLst/></p:spPr><p:txBody><a:bodyPr/><a:lstStyle><a:lvl1pPr marL="0" indent="0"><a:spcBef><a:spcPts val="600"/></a:spcBef><a:buNone/><a:defRPr sz="3200"/></a:lvl1pPr></a:lstStyle><a:p><a:r><a:rPr lang="en-US" smtClean="0"/><a:t>Click icon to add picture</a:t></a:r><a:endParaRPr lang="en-US" dirty="0"/></a:p></p:txBody></p:sp><p:sp><p:nvSpPr><p:cNvPr id="4" name="Text Placeholder 3"/><p:cNvSpPr><a:spLocks noGrp="1"/></p:cNvSpPr><p:nvPr><p:ph type="body" sz="half" idx="2"/></p:nvPr></p:nvSpPr><p:spPr><a:xfrm><a:off x="457200" y="1219200"/><a:ext cx="8229600" cy="533400"/></a:xfrm></p:spPr><p:txBody><a:bodyPr anchor="ctr" anchorCtr="0"/><a:lstStyle><a:lvl1pPr marL="0" indent="0" algn="l"><a:buFontTx/><a:buNone/><a:defRPr sz="1400"/></a:lvl1pPr><a:lvl2pPr><a:defRPr sz="1200"/></a:lvl2pPr><a:lvl3pPr><a:defRPr sz="1000"/></a:lvl3pPr><a:lvl4pPr><a:defRPr sz="900"/></a:lvl4pPr><a:lvl5pPr><a:defRPr sz="900"/></a:lvl5pPr></a:lstStyle><a:p><a:pPr lvl="0"/><a:r><a:rPr lang="en-US" smtClean="0"/><a:t>Click to edit Master text styles</a:t></a:r></a:p></p:txBody></p:sp><p:sp><p:nvSpPr><p:cNvPr id="5" name="Date Placeholder 4"/><p:cNvSpPr><a:spLocks noGrp="1"/></p:cNvSpPr><p:nvPr><p:ph type="dt" sz="half" idx="10"/></p:nvPr></p:nvSpPr><p:spPr/><p:txBody><a:bodyPr/><a:lstStyle/><a:p><a:fld id="{33938BEC-55E3-4F9D-B5C5-76D23951C04A}" type="datetime1"><a:rPr lang="en-US" smtClean="0"/><a:pPr/><a:t>9/27/2013</a:t></a:fld><a:endParaRPr lang="en-US"/></a:p></p:txBody></p:sp><p:sp><p:nvSpPr><p:cNvPr id="6" name="Footer Placeholder 5"/><p:cNvSpPr><a:spLocks noGrp="1"/></p:cNvSpPr><p:nvPr><p:ph type="ftr" sz="quarter" idx="11"/></p:nvPr></p:nvSpPr><p:spPr/><p:txBody><a:bodyPr/><a:lstStyle/><a:p><a:endParaRPr lang="en-US"/></a:p></p:txBody></p:sp><p:sp><p:nvSpPr><p:cNvPr id="7" name="Slide Number Placeholder 6"/><p:cNvSpPr><a:spLocks noGrp="1"/></p:cNvSpPr><p:nvPr><p:ph type="sldNum" sz="quarter" idx="12"/></p:nvPr></p:nvSpPr><p:spPr/><p:txBody><a:bodyPr/><a:lstStyle/><a:p><a:fld id="{D4B5ADC2-7248-4799-8E52-477E151C3EE9}" type="slidenum"><a:rPr lang="en-US" sz="1400" b="1" smtClean="0"><a:solidFill><a:srgbClr val="FFFFFF"/></a:solidFill></a:rPr><a:pPr/><a:t>‹#›</a:t></a:fld><a:endParaRPr lang="en-US"/></a:p></p:txBody></p:sp><p:sp><p:nvSpPr><p:cNvPr id="8" name="Straight Connector 7"/><p:cNvSpPr><a:spLocks noChangeShapeType="1"/></p:cNvSpPr><p:nvPr/></p:nvSpPr><p:spPr bwMode="auto"><a:xfrm><a:off x="457200" y="6353175"/><a:ext cx="8229600" cy="0"/></a:xfrm><a:prstGeom prst="line"><a:avLst/></a:prstGeom><a:noFill/><a:ln w="9525" cap="flat" cmpd="sng" algn="ctr"><a:solidFill><a:schemeClr val="accent2"/></a:solidFill><a:prstDash val="dash"/><a:round/><a:headEnd type="none" w="med" len="med"/><a:tailEnd type="none" w="med" len="med"/></a:ln><a:effectLst/></p:spPr><p:txBody><a:bodyPr vert="horz" wrap="square" lIns="91440" tIns="45720" rIns="91440" bIns="45720" anchor="t" compatLnSpc="1"/><a:lstStyle/><a:p><a:endParaRPr lang="en-US"/></a:p></p:txBody></p:sp><p:sp><p:nvSpPr><p:cNvPr id="9" name="Shape 8"/><p:cNvSpPr><a:spLocks noChangeAspect="1"/></p:cNvSpPr><p:nvPr/></p:nvSpPr><p:spPr><a:xfrm rot="5400000"><a:off x="419100" y="6467475"/><a:ext cx="190849" cy="120314"/></a:xfrm><a:prstGeom prst="triangle"><a:avLst><a:gd name="adj" fmla="val 50000"/></a:avLst></a:prstGeom><a:solidFill><a:schemeClr val="accent2"/></a:solidFill><a:ln w="25400" cap="rnd" cmpd="sng" algn="ctr"><a:noFill/><a:prstDash val="solid"/></a:ln><a:effectLst/></p:spPr><p:style><a:lnRef idx="3"><a:schemeClr val="lt1"/></a:lnRef><a:fillRef idx="1"><a:schemeClr val="accent1"/></a:fillRef><a:effectRef idx="1"><a:schemeClr val="accent1"/></a:effectRef><a:fontRef idx="minor"><a:schemeClr val="lt1"/></a:fontRef></p:style><p:txBody><a:bodyPr anchor="ctr"/><a:lstStyle/><a:p><a:pPr algn="ctr"/><a:endParaRPr lang="en-US"/></a:p></p:txBody></p:sp><p:sp><p:nvSpPr><p:cNvPr id="10" name="Rectangle 9"/><p:cNvSpPr/><p:nvPr/></p:nvSpPr><p:spPr><a:xfrm><a:off x="457200" y="500856"/><a:ext cx="182880" cy="685800"/></a:xfrm><a:prstGeom prst="rect"><a:avLst/></a:prstGeom><a:solidFill><a:schemeClr val="accent1"/></a:solidFill><a:ln w="6350" cap="rnd" cmpd="sng" algn="ctr"><a:noFill/><a:prstDash val="solid"/></a:ln><a:effectLst/></p:spPr><p:style><a:lnRef idx="3"><a:schemeClr val="lt1"/></a:lnRef><a:fillRef idx="1"><a:schemeClr val="accent1"/></a:fillRef><a:effectRef idx="1"><a:schemeClr val="accent1"/></a:effectRef><a:fontRef idx="minor"><a:schemeClr val="lt1"/></a:fontRef></p:style><p:txBody><a:bodyPr anchor="ctr"/><a:lstStyle/><a:p><a:pPr algn="ctr"/><a:endParaRPr lang="en-US"/></a:p></p:txBody></p:sp></p:spTree></p:cSld><p:clrMapOvr><a:masterClrMapping/></p:clrMapOvr></p:sldLayout>